AUTHORS
LICENSE
MANIFEST.in
README.md
setup.cfg
setup.py
django_apscheduler/__init__.py
django_apscheduler/admin.py
django_apscheduler/apps.py
django_apscheduler/jobstores.py
django_apscheduler/models.py
django_apscheduler/util.py
django_apscheduler/migrations/__init__.py
django_apscheduler_v0.6.2.egg-info/PKG-INFO
django_apscheduler_v0.6.2.egg-info/SOURCES.txt
django_apscheduler_v0.6.2.egg-info/dependency_links.txt
django_apscheduler_v0.6.2.egg-info/not-zip-safe
django_apscheduler_v0.6.2.egg-info/requires.txt
django_apscheduler_v0.6.2.egg-info/top_level.txt
docs/changelog.md
docs/releasing.md
docs/screenshots/execution_overview.png
docs/screenshots/job_overview.png
docs/screenshots/run_now.png