Metadata-Version: 2.1
Name: django-apscheduler-v0.6.2
Version: 1.0.0
Summary: APScheduler for Django
Home-page: http://github.com/jcass77/django-apscheduler
Author: Jarek Glowacki, Stas Kaledin, John Cass
Author-email: jarekwg@gmail.com, staskaledin@gmail.com, john.cass77@gmail.com
License: MIT
Keywords: django apscheduler django-apscheduler
Platform: UNKNOWN
Classifier: Development Status :: 4 - Beta
Classifier: Environment :: Web Environment
Classifier: Intended Audience :: Developers
Classifier: License :: OSI Approved :: MIT License
Classifier: Operating System :: OS Independent
Classifier: Programming Language :: Python
Classifier: Programming Language :: Python :: 3
Classifier: Programming Language :: Python :: 3 :: Only
Classifier: Programming Language :: Python :: 3.8
Classifier: Programming Language :: Python :: 3.9
Classifier: Programming Language :: Python :: 3.10
Classifier: Framework :: Django
Classifier: Framework :: Django :: 3.2
Classifier: Framework :: Django :: 4.0
License-File: LICENSE
License-File: AUTHORS
